<?xml version="1.0" encoding="utf-8"?>
<openerp>
    <data>

		<template id="assets_frontend" inherit_id="website.assets_frontend" name="Custom CSS-JS">
			<xpath expr="." position="inside">
				<link rel="stylesheet" href="/odoo_website_product_label/static/src/css/custom.css"/>
			</xpath>
		</template>
		
		
		<!-- Product item used by /shop inherit -->
		<template id="product_listing_page_extended" inherit_id='website_sale.products_item'>

			<!-- Add Label on Shop/Product Listing Page -->
			<xpath expr="//div[@class='ribbon-wrapper']" position="after">
				<t t-if="product.select_label">
					 <div t-att-class="product.select_label.position">
						<span>
							<img class="img img-responsive"
								t-att-src="website.image_url(product.select_label, 'image')" t-att-title="product.select_label.name"
								t-attf-style="height:#{product.select_label.height or '0px'};
											  width:#{product.select_label.width or '0px'};
											  margin-left:#{product.select_label.margin_left or '0px'};
											  margin-right:#{product.select_label.margin_right or '0px'};
											  margin-top:#{product.select_label.margin_top or '0px'};
											  margin-bottom:#{product.select_label.margin_bottom or '0px'};" />
						</span>
					 </div>
		      	</t>
			</xpath>
		
		</template>


		<!-- /shop/product single product page -->
		<template id="single_product_page_extended" inherit_id='website_sale.product'>

			<!-- Add Label on Single Product Page -->
			<xpath expr="//div[@class='col-sm-7']" position="inside">
				<t t-if="product.select_label">
					 <div t-att-class="product.select_label.position">
						<span>
							<img class="img img-responsive"
								t-att-src="website.image_url(product.select_label, 'image')" t-att-title="product.select_label.name"
								t-attf-style="height:#{product.select_label.height or '0px'};
											  width:#{product.select_label.width or '0px'};
											  margin-left:#{product.select_label.margin_left or '0px'};
											  margin-right:#{product.select_label.margin_right or '0px'};
											  margin-top:#{product.select_label.margin_top or '0px'};
											  margin-bottom:#{product.select_label.margin_bottom or '0px'};" />
						</span>
					 </div>
		      	</t>
			</xpath>
		
		</template>
			
		
    </data>
</openerp>
